{"P4": {"labels": ["documentation"], "postTitle": "\u5b66\u4e60\u7b14\u8bb0\uff1a2024\u5e7412\u67089\u65e5", "postUrl": "post/xue-xi-bi-ji-%EF%BC%9A2024-nian-12-yue-9-ri.html", "createdDate": "2024-12-09", "dateLabelColor": "#bc4c00"}, "P3": {"labels": ["documentation"], "postTitle": "\u5b66\u4e60\u7b14\u8bb0\uff1a2024-12-08", "postUrl": "post/xue-xi-bi-ji-%EF%BC%9A2024-12-08.html", "createdDate": "2024-12-09", "dateLabelColor": "#bc4c00"}, "P2": {"labels": ["documentation"], "postTitle": "HI", "postUrl": "post/HI.html", "createdDate": "2024-12-06", "dateLabelColor": "#bc4c00"}, "labelColorDict": {"bug": "#d73a4a", "documentation": "#0075ca", "duplicate": "#cfd3d7", "enhancement": "#a2eeef", "good first issue": "#7057ff", "help wanted": "#008672", "invalid": "#e4e669", "question": "#d876e3", "wontfix": "#ffffff"}}